Metadata-Version: 1.0
Name: dsnd-distributions-pri
Version: 1.0
Summary: Gaussian distributions and Binomial distributions
Home-page: UNKNOWN
Author: Priadi
Author-email: priaditeguhw@gmail.com
License: UNKNOWN
Platform: UNKNOWN
